mrzscanner/__init__.py
mrzscanner/scanner.py
mrzscanner/utils.py
mrzscanner/det/__init__.py
mrzscanner/det/infer.py
mrzscanner/rec/__init__.py
mrzscanner/rec/infer.py
mrzscanner/spotting/__init__.py
mrzscanner/spotting/infer.py
mrzscanner/spotting/ckpt/README.md
mrzscanner_docsaid-1.0.7.dist-info/licenses/LICENSE
mrzscanner_docsaid-1.0.7.dist-info/METADATA
mrzscanner_docsaid-1.0.7.dist-info/WHEEL
mrzscanner_docsaid-1.0.7.dist-info/top_level.txt
mrzscanner_docsaid-1.0.7.dist-info/RECORD
