Metadata-Version: 2.4
Name: mrzscanner_docsaid
Version: 1.0.7
Summary: A Python package for recognizing and extracting MRZ from visa and passport documents.
Home-page: https://github.com/DocsaidLab/MRZScanner.git
License: Apache License 2.0
Classifier: Development Status :: 5 - Production/Stable
Classifier: License :: OSI Approved :: Apache Software License
Classifier: Intended Audience :: Developers
Classifier: Intended Audience :: Science/Research
Classifier: Operating System :: OS Independent
Classifier: Programming Language :: Python :: 3.10
Classifier: Programming Language :: Python :: 3.11
Classifier: Programming Language :: Python :: 3.12
Classifier: Topic :: Software Development :: Libraries
Classifier: Topic :: Software Development :: Libraries :: Python Modules
License-File: LICENSE
Requires-Dist: capybara_docsaid<1.0.0,>=0.8.0
Dynamic: license-file
